hepbrowse/__init__.py
hepbrowse/settings.py
hepbrowse/viewer.py
hepbrowse/css/hepbrowse.tcss
hepbrowse/css/plot_tab.tcss
hepbrowse/css/settings_screen.tcss
hepbrowse/data/__init__.py
hepbrowse/data/data_manager.py
hepbrowse/data/h5_loader.py
hepbrowse/data/loader_base.py
hepbrowse/data/root_loader.py
hepbrowse/docs/welcome.md
hepbrowse/helpers/__init__.py
hepbrowse/helpers/loader_factory.py
hepbrowse/helpers/tree_builder.py
hepbrowse/plotting/__init__.py
hepbrowse/plotting/histogram_engine.py
hepbrowse/plugins/__init__.py
hepbrowse/plugins/api.py
hepbrowse/plugins/loader.py
hepbrowse/plugins/plot/__init__.py
hepbrowse/plugins/plot/plugin.py
hepbrowse/widgets/__init__.py
hepbrowse/widgets/plot_tab.py
hepbrowse-0.1.4.dist-info/METADATA
hepbrowse-0.1.4.dist-info/WHEEL
hepbrowse-0.1.4.dist-info/entry_points.txt
hepbrowse-0.1.4.dist-info/top_level.txt
hepbrowse-0.1.4.dist-info/RECORD
