Metadata-Version: 2.4
Name: hepbrowse
Version: 0.1.4
Summary: Interactive TUI for exploring HEP data files
Author: Leonardo Splendori
Project-URL: Homepage, https://github.com/Leonardo-Splendori/HEPBrowse
Project-URL: Issues, https://github.com/Leonardo-Splendori/HEPBrowse/issues
Requires-Python: >=3.10
Requires-Dist: textual
Requires-Dist: textual-plotext
Requires-Dist: click
Requires-Dist: numpy
Requires-Dist: h5py
Requires-Dist: uproot
Requires-Dist: awkward
Requires-Dist: pyyaml
